simple_html/__init__.py
simple_html/py.typed
simple_html/utils.cpython-312-x86_64-linux-gnu.so
simple_html/utils.py
simple_html/utils__mypyc.cpython-312-x86_64-linux-gnu.so
simple_html-3.0.0.dist-info/METADATA
simple_html-3.0.0.dist-info/WHEEL
simple_html-3.0.0.dist-info/top_level.txt
simple_html-3.0.0.dist-info/RECORD
simple_html-3.0.0.dist-info/licenses/LICENSE
