Metadata-Version: 2.4
Name: simple-html
Version: 3.0.0
Summary: Template-less HTML rendering in Python
Home-page: https://github.com/keithasaurus/simple_html
Author: Keith Philpott
Project-URL: Homepage, https://github.com/keithasaurus/simple_html
Keywords: html,type hints
Classifier: Development Status :: 5 - Production/Stable
Classifier: Environment :: Console
Classifier: Environment :: MacOS X
Classifier: Environment :: Web Environment
Classifier: Intended Audience :: Developers
Classifier: Operating System :: MacOS
Classifier: Operating System :: Microsoft :: Windows
Classifier: Operating System :: POSIX :: Linux
Classifier: Operating System :: Unix
Classifier: Topic :: Software Development :: Libraries :: Python Modules
Classifier: Topic :: Utilities
Classifier: Typing :: Typed
Requires-Python: >=3.9
License-File: LICENSE
Dynamic: home-page
Dynamic: license-file
Dynamic: requires-python
